LICENSE.txt
README.md
setup.cfg
setup.py
PythonApi_CogentDataHub/DataHubConnection.py
PythonApi_CogentDataHub/PID.py
PythonApi_CogentDataHub/TrendChart.py
PythonApi_CogentDataHub/__init__.py
PythonApi_CogentDataHub/lispparse.py
PythonApi_CogentDataHub.egg-info/PKG-INFO
PythonApi_CogentDataHub.egg-info/SOURCES.txt
PythonApi_CogentDataHub.egg-info/dependency_links.txt
PythonApi_CogentDataHub.egg-info/requires.txt
PythonApi_CogentDataHub.egg-info/top_level.txt