Metadata-Version: 2.1
Name: PythonApi-CogentDataHub
Version: 0.13
Summary: Python Api for Cogent DataHub
Home-page: https://github.com/cyuenSkkynet/PythonApi_CogentDataHub
Download-URL: https://github.com/cyuenSkkynet/PythonApi_CogentDataHub/archive/refs/tags/v0.13.tar.gz
Author: Colin Yuen
Author-email: colin.yuen@skkynet.com
License: MIT
Keywords: Cogent,DataHub,Api,Python
Classifier: Development Status :: 3 - Alpha
Classifier: Intended Audience :: Developers
Classifier: Topic :: Software Development :: Build Tools
Classifier: License :: OSI Approved :: MIT License
Classifier: Programming Language :: Python :: 3
Classifier: Programming Language :: Python :: 3.7
Classifier: Programming Language :: Python :: 3.8
Classifier: Programming Language :: Python :: 3.9
Classifier: Programming Language :: Python :: 3.10
Classifier: Programming Language :: Python :: 3.11
Classifier: Programming Language :: Python :: 3.12
License-File: LICENSE.txt
